<?xml version="1.0" encoding="UTF-8"?>

<Warnings> 
  <Warning error="false" xpath="id('sv1#area8#page8#inu7')" rootXPath="id('sv1')" key="UNSPECIFIED_SORTING_ATTRIBUTE" label="Promozioni attive in negozio"> 
    <Message>Sorting attribute are unspecified for the component 'Promozioni attive in negozio'</Message> 
  </Warning>  
  <Warning error="true" xpath="id('sv1#area8#page8#inu7#su7#acond2')" rootXPath="id('sv1')" key="" label="valida in negozio"> 
    <Message>Invalid value '1' specified for the condition 'valida in negozio': 'true' or 'false' must be specified</Message> 
  </Warning>  
  <Warning xpath="id('sv1#area8#page8#inu7')" rootXPath="id('sv1')" key="MISSING_MANDATORY_INPUT_PARAMETER" label="Promozioni attive in negozio"> 
    <Message>The mandatory input parameter 'da prodotto a promozioni [oid]' is not provided to the component 'Promozioni attive in negozio'</Message> 
  </Warning> 
</Warnings>
